keithleygui/__init__.py
keithleygui/main.py
keithleygui/main.ui
keithleygui/pyqtplot_canvas.py
keithleygui/config/__init__.py
keithleygui/config/base.py
keithleygui/config/main.py
keithleygui/config/user.py
keithleygui/pyqt_labutils/__init__.py
keithleygui/pyqt_labutils/animated_widgets.py
keithleygui/pyqt_labutils/connection_dialog.py
keithleygui/pyqt_labutils/connection_dialog.ui
keithleygui/pyqt_labutils/dark_mode_support.py
keithleygui/pyqt_labutils/led_indicator.py
keithleygui/pyqt_labutils/list_entry_widget.py
keithleygui/pyqt_labutils/misc.py
keithleygui/pyqt_labutils/notify.py
keithleygui/pyqt_labutils/scientific_spinbox.py
keithleygui/pyqt_labutils/settings_pane.py
keithleygui/pyqt_labutils/spinner.py
keithleygui-1.2.1.dist-info/LICENSE.txt
keithleygui-1.2.1.dist-info/METADATA
keithleygui-1.2.1.dist-info/WHEEL
keithleygui-1.2.1.dist-info/entry_points.txt
keithleygui-1.2.1.dist-info/top_level.txt
keithleygui-1.2.1.dist-info/RECORD
