Metadata-Version: 2.1
Name: keithleygui
Version: 1.2.1
Summary: A GUI for the Keithley 2600 series
Home-page: https://github.com/oe-fet/keithleygui.git
Author: Sam Schott
Author-email: ss2151@cam.ac.uk
License: MIT
Keywords: keithleygui
Platform: UNKNOWN
Classifier: License :: OSI Approved :: MIT License
Classifier: Operating System :: Unix
Classifier: Programming Language :: Python
Classifier: Programming Language :: Python :: 3.6
Classifier: Programming Language :: Python :: 3.7
Classifier: Programming Language :: Python :: 3.8
Requires-Python: >=3.6
